nebulacli.py
nebulacli-0.3.3.dist-info/LICENSE
nebulacli-0.3.3.dist-info/METADATA
nebulacli-0.3.3.dist-info/WHEEL
nebulacli-0.3.3.dist-info/entry_points.txt
nebulacli-0.3.3.dist-info/top_level.txt
nebulacli-0.3.3.dist-info/RECORD
