Metadata-Version: 2.1
Name: nebulacli
Version: 0.3.3
Summary: UNKNOWN
Home-page: https://github.com/tedivm/nebula-cli
Author: Robert Hafner
Author-email: tedivm@tedivm.com
License: UNKNOWN
Download-URL: https://github.com/tedivm/nebula-cli/archive/v0.3.3.tar.gz
Platform: UNKNOWN
Classifier: Development Status :: 4 - Beta
Classifier: License :: OSI Approved :: MIT License
Classifier: Intended Audience :: Developers
Classifier: Programming Language :: Python :: 3
Classifier: Environment :: Console
Requires-Python: >=3
Requires-Dist: click (<6.0,>=5.0)
Requires-Dist: requests (<3,>=2.18.0)
Provides-Extra: dev
Requires-Dist: twine ; extra == 'dev'
Requires-Dist: wheel ; extra == 'dev'
